[
    {
        "title": "Buy Groceries",
        "description": "Need to buy milk, eggs, and vegetables.",
        "category": "Personal Task",
        "dueDate": "2025-02-25",
        "priority": "High",
        "reminder": true,
        "reminderTime": "10:00",
        "email": "zubayer.nahin@gmail.com",
        "displayName": "mj jawad",
        "photoURL": "https://lh3.googleusercontent.com/a/ACg8ocK9TOjzzJTJ-JnK_vIABiqu5T4rk-QI0xTjC8ev_lhdmPfCrcDV=s96-c"
    },
    {
        "title": "Project Meeting",
        "description": "Team meeting for the TrackWise project updates.",
        "category": "Work",
        "dueDate": "2025-02-26",
        "priority": "Medium",
        "reminder": false,
        "reminderTime": "",
        "email": "zubayer.nahin@gmail.com",
        "displayName": "mj jawad",
        "photoURL": "https://lh3.googleusercontent.com/a/ACg8ocK9TOjzzJTJ-JnK_vIABiqu5T4rk-QI0xTjC8ev_lhdmPfCrcDV=s96-c"
    },
    {
        "title": "Gym Session",
        "description": "Full body workout at the gym.",
        "category": "Health",
        "dueDate": "2025-02-27",
        "priority": "Low",
        "reminder": true,
        "reminderTime": "19:30",
        "email": "zubayer.nahin@gmail.com",
        "displayName": "mj jawad",
        "photoURL": "https://lh3.googleusercontent.com/a/ACg8ocK9TOjzzJTJ-JnK_vIABiqu5T4rk-QI0xTjC8ev_lhdmPfCrcDV=s96-c"
    },
    {
        "title": "Client Presentation",
        "description": "Prepare slides for the upcoming client meeting.",
        "category": "Work",
        "dueDate": "2025-02-28",
        "priority": "Urgent",
        "reminder": true,
        "reminderTime": "08:30",
        "email": "zubayer.nahin@gmail.com",
        "displayName": "mj jawad",
        "photoURL": "https://lh3.googleusercontent.com/a/ACg8ocK9TOjzzJTJ-JnK_vIABiqu5T4rk-QI0xTjC8ev_lhdmPfCrcDV=s96-c"
    },
    {
        "title": "Doctor Appointment",
        "description": "Routine health check-up with Dr. Rahman.",
        "category": "Health",
        "dueDate": "2025-03-01",
        "priority": "High",
        "reminder": false,
        "reminderTime": "",
        "email": "zubayer.nahin@gmail.com",
        "displayName": "mj jawad",
        "photoURL": "https://lh3.googleusercontent.com/a/ACg8ocK9TOjzzJTJ-JnK_vIABiqu5T4rk-QI0xTjC8ev_lhdmPfCrcDV=s96-c"
    },
    {
        "title": "Family Dinner",
        "description": "Dinner with family at a new restaurant.",
        "category": "Personal Task",
        "dueDate": "2025-03-02",
        "priority": "Medium",
        "reminder": true,
        "reminderTime": "20:00",
        "email": "zubayer.nahin@gmail.com",
        "displayName": "mj jawad",
        "photoURL": "https://lh3.googleusercontent.com/a/ACg8ocK9TOjzzJTJ-JnK_vIABiqu5T4rk-QI0xTjC8ev_lhdmPfCrcDV=s96-c"
    },
    {
        "title": "Read a Book",
        "description": "Finish reading 'Atomic Habits' by James Clear.",
        "category": "Personal Development",
        "dueDate": "2025-03-03",
        "priority": "Low",
        "reminder": false,
        "reminderTime": "",
        "email": "zubayer.nahin@gmail.com",
        "displayName": "mj jawad",
        "photoURL": "https://lh3.googleusercontent.com/a/ACg8ocK9TOjzzJTJ-JnK_vIABiqu5T4rk-QI0xTjC8ev_lhdmPfCrcDV=s96-c"
    },
    {
        "title": "Submit Assignment",
        "description": "Complete and submit the DBMS assignment before deadline.",
        "category": "Education",
        "dueDate": "2025-03-04",
        "priority": "Urgent",
        "reminder": true,
        "reminderTime": "23:00",
        "email": "zubayer.nahin@gmail.com",
        "displayName": "mj jawad",
        "photoURL": "https://lh3.googleusercontent.com/a/ACg8ocK9TOjzzJTJ-JnK_vIABiqu5T4rk-QI0xTjC8ev_lhdmPfCrcDV=s96-c"
    },
    {
        "title": "Buy Groceries",
        "description": "Need to buy milk, eggs, and vegetables.",
        "category": "Personal Task",
        "dueDate": "2025-02-25",
        "priority": "High",
        "reminder": true,
        "reminderTime": "10:00",
        "email": "mahin1575@gmail.com",
        "displayName": "mj jawad",
        "photoURL": "https://lh3.googleusercontent.com/a/ACg8ocK9TOjzzJTJ-JnK_vIABiqu5T4rk-QI0xTjC8ev_lhdmPfCrcDV=s96-c"
    },
    {
        "title": "Project Meeting",
        "description": "Team meeting for the TrackWise project updates.",
        "category": "Work",
        "dueDate": "2025-02-26",
        "priority": "Medium",
        "reminder": false,
        "reminderTime": "",
        "email": "mahin1575@gmail.com",
        "displayName": "mj jawad",
        "photoURL": "https://lh3.googleusercontent.com/a/ACg8ocK9TOjzzJTJ-JnK_vIABiqu5T4rk-QI0xTjC8ev_lhdmPfCrcDV=s96-c"
    },
    {
        "title": "Gym Session",
        "description": "Full body workout at the gym.",
        "category": "Health",
        "dueDate": "2025-02-27",
        "priority": "Low",
        "reminder": true,
        "reminderTime": "19:30",
        "email": "mahin1575@gmail.com",
        "displayName": "mj jawad",
        "photoURL": "https://lh3.googleusercontent.com/a/ACg8ocK9TOjzzJTJ-JnK_vIABiqu5T4rk-QI0xTjC8ev_lhdmPfCrcDV=s96-c"
    },
    {
        "title": "Client Presentation",
        "description": "Prepare slides for the upcoming client meeting.",
        "category": "Work",
        "dueDate": "2025-02-28",
        "priority": "Urgent",
        "reminder": true,
        "reminderTime": "08:30",
        "email": "mahin1575@gmail.com",
        "displayName": "mj jawad",
        "photoURL": "https://lh3.googleusercontent.com/a/ACg8ocK9TOjzzJTJ-JnK_vIABiqu5T4rk-QI0xTjC8ev_lhdmPfCrcDV=s96-c"
    },
    {
        "title": "Doctor Appointment",
        "description": "Routine health check-up with Dr. Rahman.",
        "category": "Health",
        "dueDate": "2025-03-01",
        "priority": "High",
        "reminder": false,
        "reminderTime": "",
        "email": "mahin1575@gmail.com",
        "displayName": "mj jawad",
        "photoURL": "https://lh3.googleusercontent.com/a/ACg8ocK9TOjzzJTJ-JnK_vIABiqu5T4rk-QI0xTjC8ev_lhdmPfCrcDV=s96-c"
    },
    {
        "title": "Family Dinner",
        "description": "Dinner with family at a new restaurant.",
        "category": "Personal Task",
        "dueDate": "2025-03-02",
        "priority": "Medium",
        "reminder": true,
        "reminderTime": "20:00",
        "email": "mahin1575@gmail.com",
        "displayName": "mj jawad",
        "photoURL": "https://lh3.googleusercontent.com/a/ACg8ocK9TOjzzJTJ-JnK_vIABiqu5T4rk-QI0xTjC8ev_lhdmPfCrcDV=s96-c"
    },
    {
        "title": "Read a Book",
        "description": "Finish reading 'Atomic Habits' by James Clear.",
        "category": "Personal Development",
        "dueDate": "2025-03-03",
        "priority": "Low",
        "reminder": false,
        "reminderTime": "",
        "email": "mahin1575@gmail.com",
        "displayName": "mj jawad",
        "photoURL": "https://lh3.googleusercontent.com/a/ACg8ocK9TOjzzJTJ-JnK_vIABiqu5T4rk-QI0xTjC8ev_lhdmPfCrcDV=s96-c"
    },
    {
        "title": "Submit Assignment",
        "description": "Complete and submit the DBMS assignment before deadline.",
        "category": "Education",
        "dueDate": "2025-03-04",
        "priority": "Urgent",
        "reminder": true,
        "reminderTime": "23:00",
        "email": "mahin1575@gmail.com",
        "displayName": "mj jawad",
        "photoURL": "https://lh3.googleusercontent.com/a/ACg8ocK9TOjzzJTJ-JnK_vIABiqu5T4rk-QI0xTjC8ev_lhdmPfCrcDV=s96-c"
    }
]